providers/__init__.py
providers-0.0.2.dist-info/LICENSE
providers-0.0.2.dist-info/WHEEL
providers-0.0.2.dist-info/METADATA
providers-0.0.2.dist-info/RECORD
